twitterstatsazure/__init__.py
twitterstatsazure/api_client.py
twitterstatsazure/run.py
twitterstatsazure/secrets.py
twitterstatsazure/stats.py
twitterstatsazure/storage.py
twitterstatsazure-0.1.2.dist-info/AUTHORS
twitterstatsazure-0.1.2.dist-info/LICENCE
twitterstatsazure-0.1.2.dist-info/METADATA
twitterstatsazure-0.1.2.dist-info/WHEEL
twitterstatsazure-0.1.2.dist-info/top_level.txt
twitterstatsazure-0.1.2.dist-info/RECORD
